e13tools/__init__.py
e13tools/__version__.py
e13tools/core.py
e13tools/math.py
e13tools/numpy.py
e13tools/pyplot.py
e13tools/utils.py
e13tools/sampling/__init__.py
e13tools/sampling/lhs.py
e13tools/tests/__init__.py
e13tools/tests/test_core.py
e13tools/tests/test_math.py
e13tools/tests/test_numpy.py
e13tools/tests/test_pyplot.py
e13tools/tests/test_sampling.py
e13tools/tests/test_utils.py
e13tools-0.9.6.dist-info/LICENSE
e13tools-0.9.6.dist-info/METADATA
e13tools-0.9.6.dist-info/WHEEL
e13tools-0.9.6.dist-info/top_level.txt
e13tools-0.9.6.dist-info/RECORD
