Metadata-Version: 1.2
Name: e13tools
Version: 0.9.6
Summary: A collection of utility functions
Home-page: https://e13tools.readthedocs.io
Author: Ellert van der Velden
Author-email: ellert_vandervelden@outlook.com
License: BSD-3
Keywords: e13tools utilities latin hypercube sampling math tools
Platform: Windows
Platform: Mac OS-X
Platform: Linux
Platform: Unix
Classifier: Development Status :: 3 - Alpha
Classifier: Intended Audience :: Developers
Classifier: Intended Audience :: Science/Research
Classifier: License :: OSI Approved :: BSD License
Classifier: Natural Language :: English
Classifier: Operating System :: MacOS
Classifier: Operating System :: Microsoft :: Windows
Classifier: Operating System :: Unix
Classifier: Programming Language :: Python
Classifier: Programming Language :: Python :: 3
Classifier: Programming Language :: Python :: 3.6
Classifier: Programming Language :: Python :: 3.7
Classifier: Programming Language :: Python :: 3.8
Classifier: Programming Language :: Python :: 3.9
Classifier: Topic :: Software Development :: Libraries :: Python Modules
Classifier: Topic :: Utilities
Requires-Python: >=3.6, <4
